yamole.py
yamole-2.1.7.dist-info/METADATA
yamole-2.1.7.dist-info/RECORD
yamole-2.1.7.dist-info/WHEEL
yamole-2.1.7.dist-info/top_level.txt
