Metadata-Version: 2.1
Name: yamole
Version: 2.1.7
Summary: A YAML parser that resolves JSON references
Home-page: UNKNOWN
Author: Yago González
License: MIT
Project-URL: Source, https://github.com/YagoGG/yamole/
Project-URL: Tracker, https://github.com/YagoGG/yamole/issues
Keywords: yaml json references parser openapi swagger
Platform: UNKNOWN
Classifier: Development Status :: 5 - Production/Stable
Classifier: Intended Audience :: Developers
Classifier: License :: DFSG approved
Classifier: License :: OSI Approved
Classifier: License :: OSI Approved :: MIT License
Classifier: Programming Language :: Python :: 2
Classifier: Programming Language :: Python :: 2.7
Classifier: Programming Language :: Python :: 3
Classifier: Programming Language :: Python :: 3.6
Requires-Dist: pyyaml
